{
  "matej70": {
    "enabled": 1,
    "hidden": true,
    "description": "NixOS",
    "nixexprinput": "src",
    "nixexprpath": "build.nix",
    "checkinterval": 600,
    "schedulingshares": 100,
    "enableemail": false,
    "emailoverride": "",
    "keepnr": 10,
    "inputs": {
      "src": {
        "type": "git",
        "value": "https://github.com/matejc/helper_scripts.git",
        "emailresponsible": false
      },
      "name": {
        "type": "string",
        "value": "matej70",
        "emailresponsible": false
      }
    }
  },
  "matej80": {
    "enabled": 1,
    "hidden": true,
    "description": "NixOS",
    "nixexprinput": "src",
    "nixexprpath": "build.nix",
    "checkinterval": 600,
    "schedulingshares": 100,
    "enableemail": false,
    "emailoverride": "",
    "keepnr": 10,
    "inputs": {
      "src": {
        "type": "git",
        "value": "https://github.com/matejc/helper_scripts.git",
        "emailresponsible": false
      },
      "name": {
        "type": "string",
        "value": "matej80",
        "emailresponsible": false
      }
    }
  },
  "nixko": {
    "enabled": 1,
    "hidden": true,
    "description": "NixOS",
    "nixexprinput": "src",
    "nixexprpath": "build.nix",
    "checkinterval": 600,
    "schedulingshares": 100,
    "enableemail": false,
    "emailoverride": "",
    "keepnr": 10,
    "inputs": {
      "src": {
        "type": "git",
        "value": "https://github.com/matejc/helper_scripts.git",
        "emailresponsible": false
      },
      "name": {
        "type": "string",
        "value": "nixko",
        "emailresponsible": false
      }
    }
  },
  "wsl": {
    "enabled": 1,
    "hidden": true,
    "description": "NixOS",
    "nixexprinput": "src",
    "nixexprpath": "build.nix",
    "checkinterval": 600,
    "schedulingshares": 100,
    "enableemail": false,
    "emailoverride": "",
    "keepnr": 10,
    "inputs": {
      "src": {
        "type": "git",
        "value": "https://github.com/matejc/helper_scripts.git",
        "emailresponsible": false
      },
      "name": { "type": "string", "value": "wsl", "emailresponsible": false }
    }
  },
  "packages": {
    "enabled": 1,
    "hidden": true,
    "description": "Extra Nix packages",
    "nixexprinput": "src",
    "nixexprpath": "build.nix",
    "checkinterval": 600,
    "schedulingshares": 100,
    "enableemail": false,
    "emailoverride": "",
    "keepnr": 10,
    "inputs": {
      "src": {
        "type": "git",
        "value": "https://github.com/matejc/helper_scripts.git",
        "emailresponsible": false
      },
      "name": {
        "type": "string",
        "value": "packages",
        "emailresponsible": false
      }
    }
  },
  "nixpkgs": {
    "enabled": 1,
    "hidden": true,
    "description": "Nix packages (master)",
    "nixexprinput": "helper_scripts",
    "nixexprpath": "hydras/packages.nix",
    "checkinterval": 600,
    "schedulingshares": 100,
    "enableemail": false,
    "emailoverride": "",
    "keepnr": 10,
    "inputs": {
      "helper_scripts": {
        "type": "git",
        "value": "https://github.com/matejc/helper_scripts.git",
        "emailresponsible": false
      },
      "nixpkgs": {
        "type": "git",
        "value": "https://github.com/matejc/nixpkgs.git",
        "emailresponsible": false
      },
      "attrs": {
        "type": "nix",
        "value": "[\"curl\"]",
        "emailresponsible": false
      }
    }
  },
  "cachyos-kernel": {
    "enabled": 1,
    "hidden": true,
    "description": "CachyOS kernel for NixOS",
    "nixexprinput": "helper_scripts",
    "nixexprpath": "build.nix",
    "checkinterval": 600,
    "schedulingshares": 100,
    "enableemail": false,
    "emailoverride": "",
    "keepnr": 10,
    "inputs": {
      "helper_scripts": {
        "type": "git",
        "value": "https://github.com/matejc/helper_scripts.git",
        "emailresponsible": false
      },
      "nix-cachyos-kernel": {
        "type": "git",
        "value": "https://github.com/xddxdd/nix-cachyos-kernel.git",
        "emailresponsible": false
      },
      "name": {
        "type": "string",
        "value": "nix-cachyos-kernel",
        "emailresponsible": false
      }
    }
  }
}
